hns_utils/__init__.py
hns_utils-20.4.1.dist-info/LICENSE
hns_utils-20.4.1.dist-info/METADATA
hns_utils-20.4.1.dist-info/WHEEL
hns_utils-20.4.1.dist-info/top_level.txt
hns_utils-20.4.1.dist-info/RECORD
